paramz/__init__.py
paramz/__version__.py
paramz/caching.py
paramz/domains.py
paramz/model.py
paramz/param.py
paramz/parameterized.py
paramz/ties_and_remappings.py
paramz/transformations.py
paramz/core/__init__.py
paramz/core/constrainable.py
paramz/core/gradcheckable.py
paramz/core/index_operations.py
paramz/core/indexable.py
paramz/core/lists_and_dicts.py
paramz/core/nameable.py
paramz/core/observable.py
paramz/core/observable_array.py
paramz/core/parameter_core.py
paramz/core/parentable.py
paramz/core/pickleable.py
paramz/core/updateable.py
paramz/optimization/__init__.py
paramz/optimization/optimization.py
paramz/optimization/scg.py
paramz/optimization/stochastics.py
paramz/optimization/verbose_optimization.py
paramz/tests/__init__.py
paramz/tests/cacher_tests.py
paramz/tests/index_operations_tests.py
paramz/tests/lists_and_dicts_tests.py
paramz/tests/observable_tests.py
paramz/tests/parameterized_tests.py
paramz/tests/pickle_tests.py
paramz-0.0.11.dist-info/DESCRIPTION.rst
paramz-0.0.11.dist-info/METADATA
paramz-0.0.11.dist-info/RECORD
paramz-0.0.11.dist-info/WHEEL
paramz-0.0.11.dist-info/metadata.json
paramz-0.0.11.dist-info/top_level.txt
