Metadata-Version: 2.0
Name: paramz
Version: 0.0.11
Summary: The Parameterization Framework
Home-page: https://github.com/mzwiessele/paramz
Author: Max Zwiessele
Author-email: ibinbei@gmail.com
License: BSD 3-clause
Keywords: machine-learning gaussian-processes kernels
Platform: UNKNOWN
Classifier: License :: OSI Approved :: BSD License
Classifier: Natural Language :: English
Classifier: Operating System :: MacOS :: MacOS X
Classifier: Operating System :: Microsoft :: Windows
Classifier: Operating System :: POSIX :: Linux
Classifier: Programming Language :: Python :: 2.7
Classifier: Programming Language :: Python :: 3.3
Classifier: Programming Language :: Python :: 3.4
Classifier: Programming Language :: Python :: 3.5
Classifier: Topic :: Scientific/Engineering :: Artificial Intelligence
Requires-Dist: numpy (>=1.7)
Requires-Dist: scipy
Requires-Dist: six
